jupyter_packaging/__init__.py
jupyter_packaging/__main__.py
jupyter_packaging/build_api.py
jupyter_packaging/setupbase.py
jupyter_packaging-0.12.2.dist-info/METADATA
jupyter_packaging-0.12.2.dist-info/WHEEL
jupyter_packaging-0.12.2.dist-info/entry_points.txt
jupyter_packaging-0.12.2.dist-info/license_files/LICENSE
jupyter_packaging-0.12.2.dist-info/RECORD
