Metadata-Version: 2.1
Name: jupyter-packaging
Version: 0.12.2
Summary: Jupyter Packaging Utilities.
Project-URL: Bug Tracker, https://github.com/jupyter/jupyter-packaging/issues
Project-URL: Homepage, http://jupyter.org
Project-URL: Source, https://github.com/jupyter/jupyter-packaging/
Author-email: Jupyter Development Team <jupyter@googlegroups.com>
License: BSD 3-Clause License
Keywords: ipython,jupyter,packaging
Classifier: Intended Audience :: Developers
Classifier: Intended Audience :: Science/Research
Classifier: Intended Audience :: System Administrators
Classifier: License :: OSI Approved :: BSD License
Classifier: Programming Language :: Python
Classifier: Programming Language :: Python :: 3.10
Classifier: Programming Language :: Python :: 3.7
Classifier: Programming Language :: Python :: 3.8
Classifier: Programming Language :: Python :: 3.9
Requires-Python: >=3.7
Requires-Dist: deprecation
Requires-Dist: packaging
Requires-Dist: setuptools>=60.2.0
Requires-Dist: tomlkit
Requires-Dist: wheel
Provides-Extra: test
Requires-Dist: build; extra == 'test'
Requires-Dist: coverage; extra == 'test'
Requires-Dist: pre-commit; extra == 'test'
Requires-Dist: pytest; extra == 'test'
Requires-Dist: pytest-cov; extra == 'test'
Requires-Dist: pytest-mock; extra == 'test'
Requires-Dist: pytest-timeout; extra == 'test'
